dyff/storage/__init__.py
dyff/storage/_version.py
dyff/storage/config.py
dyff/storage/dynamic_import.py
dyff/storage/exceptions.py
dyff/storage/paths.py
dyff/storage/timestamp.py
dyff/storage/typing.py
dyff/storage/backend/__init__.py
dyff/storage/backend/base/__init__.py
dyff/storage/backend/base/auth.py
dyff/storage/backend/base/command.py
dyff/storage/backend/base/query.py
dyff/storage/backend/base/storage.py
dyff/storage/backend/gcloud/__init__.py
dyff/storage/backend/gcloud/storage.py
dyff/storage/backend/kafka/__init__.py
dyff/storage/backend/kafka/command.py
dyff/storage/backend/mock/__init__.py
dyff/storage/backend/mock/command.py
dyff/storage/backend/mongodb/__init__.py
dyff/storage/backend/mongodb/auth.py
dyff/storage/backend/mongodb/query.py
dyff/storage/backend/s3/__init__.py
dyff/storage/backend/s3/storage.py
dyff_storage-0.26.4.dist-info/licenses/LICENSE
dyff_storage-0.26.4.dist-info/licenses/NOTICE
dyff_storage-0.26.4.dist-info/METADATA
dyff_storage-0.26.4.dist-info/WHEEL
dyff_storage-0.26.4.dist-info/top_level.txt
dyff_storage-0.26.4.dist-info/RECORD
