Metadata-Version: 2.4
Name: dyff-storage
Version: 0.26.4
Summary: Python storage API for the Dyff AI auditing platform.
Author-email: Digital Safety Research Institute <contact@dsri.org>
License: Apache-2.0
Project-URL: Home, https://gitlab.com/dyff/packages/dyff-storage
Project-URL: Issues, https://gitlab.com/dyff/packages/dyff-storage/-/issues
Classifier: Development Status :: 3 - Alpha
Classifier: Intended Audience :: Science/Research
Classifier: License :: OSI Approved :: Apache Software License
Classifier: Operating System :: OS Independent
Classifier: Programming Language :: Python :: 3
Classifier: Programming Language :: Python :: 3.10
Classifier: Programming Language :: Python :: 3.11
Classifier: Programming Language :: Python :: 3.12
Classifier: Topic :: Scientific/Engineering :: Artificial Intelligence
Requires-Python: >=3.10
License-File: LICENSE
License-File: NOTICE
Requires-Dist: confluent-kafka
Requires-Dist: dyff-schema>=0.36.9
Requires-Dist: google-cloud-storage
Requires-Dist: minio==7.2.7
Requires-Dist: pydantic<3.0.0,>=2.0.0
Requires-Dist: pydantic-settings>=2.0.0
Requires-Dist: pymongo[srv]
Dynamic: license-file
